agentmq/__init__.py
agentmq/main.py
agentmq-0.0.0.dist-info/METADATA
agentmq-0.0.0.dist-info/WHEEL
agentmq-0.0.0.dist-info/top_level.txt
agentmq-0.0.0.dist-info/RECORD
