Metadata-Version: 2.1
Name: agentmq
Version: 0.0.0
Summary: Python for AgentMQ
Author: AgentMQ
Requires-Python: >=3.6
